platec.cpython-312-x86_64-linux-gnu.so
platec_src/platecmodule.cpp
pyplatec-1.4.3.dist-info/METADATA
pyplatec-1.4.3.dist-info/WHEEL
pyplatec-1.4.3.dist-info/top_level.txt
pyplatec-1.4.3.dist-info/RECORD
pyplatec-1.4.3.dist-info/licenses/LICENSE
