Metadata-Version: 2.4
Name: PyPlatec
Version: 1.4.3
Summary: Plate tectonics simulation library
Home-page: https://github.com/Mindwerks/pyplatec
Author: Federico Tomassetti, Bret Curtis
Author-email: Federico Tomassetti <f.tomassetti@gmail.com>, Bret Curtis <psi29a@gmail.com>
Maintainer-email: Bret Curtis <psi29a@gmail.com>
License-Expression: LGPL-3.0-or-later
Project-URL: Homepage, https://github.com/Mindwerks/plate-tectonics
Project-URL: Repository, https://github.com/Mindwerks/plate-tectonics
Project-URL: Issues, https://github.com/Mindwerks/plate-tectonics/issues
Keywords: plate-tectonics,simulation,worldgen,geology
Classifier: Development Status :: 5 - Production/Stable
Classifier: Intended Audience :: Developers
Classifier: Natural Language :: English
Classifier: Operating System :: OS Independent
Classifier: Programming Language :: C++
Classifier: Programming Language :: Python
Classifier: Programming Language :: Python :: 3
Classifier: Programming Language :: Python :: 3.9
Classifier: Programming Language :: Python :: 3.10
Classifier: Programming Language :: Python :: 3.11
Classifier: Programming Language :: Python :: 3.12
Classifier: Programming Language :: Python :: 3.13
Classifier: Programming Language :: Python :: 3.14
Classifier: Programming Language :: Python :: 3 :: Only
Classifier: Topic :: Scientific/Engineering
Classifier: Topic :: Software Development :: Libraries :: Python Modules
Requires-Python: >=3.9
License-File: LICENSE
Dynamic: author
Dynamic: home-page
Dynamic: license-file
Dynamic: requires-python
